{
    "relationships": [
        {
            "relationshipName": "taxpayer_account",
            "otherEntityName": "taxpayer_account",
            "relationshipType": "many-to-one",
            "otherEntityField": "id"
        }
    ],
    "fields": [
        {
            "fieldName": "serie",
            "fieldType": "String",
            "fieldValidateRules": [
                "required",
                "maxlength"
            ],
            "fieldValidateRulesMaxlength": "25"
        },
        {
            "fieldName": "folio_start",
            "fieldType": "Integer",
            "fieldValidateRules": [
                "required"
            ]
        },
        {
            "fieldName": "folio_end",
            "fieldType": "Integer",
            "fieldValidateRules": [
                "required"
            ]
        },
        {
            "fieldName": "folio_current",
            "fieldType": "Integer",
            "fieldValidateRules": [
                "required"
            ]
        },
        {
            "fieldName": "date_creation",
            "fieldType": "LocalDate",
            "fieldValidateRules": [
                "required"
            ]
        },
        {
            "fieldName": "enable",
            "fieldType": "Boolean"
        }
    ],
    "changelogDate": "20161021125221",
    "dto": "no",
    "service": "serviceImpl",
    "entityTableName": "taxpayer_series_folio",
    "pagination": "pagination"
}
